git_logger/__init__.py
git_logger/cli.py
git_logger/git_history.py
git_logger/utils.py
git_logger-0.5.dist-info/licenses/LICENSE
git_logger-0.5.dist-info/METADATA
git_logger-0.5.dist-info/WHEEL
git_logger-0.5.dist-info/entry_points.txt
git_logger-0.5.dist-info/top_level.txt
git_logger-0.5.dist-info/RECORD
