Metadata-Version: 2.4
Name: git-logger
Version: 0.5
Summary: Log preserved history contents of csv or json file in duckdb
Author: Lyubomir Georgiev
License: Apache-2.0
Project-URL: Homepage, https://github.com/LVG77/git-logger
Project-URL: Changelog, https://github.com/LVG77/git-logger/releases
Project-URL: Issues, https://github.com/LVG77/git-logger/issues
Project-URL: CI, https://github.com/LVG77/git-logger/actions
Classifier: License :: OSI Approved :: Apache Software License
Requires-Python: >=3.10
License-File: LICENSE
Requires-Dist: duckdb
Requires-Dist: click
Requires-Dist: gitpython
Provides-Extra: test
Requires-Dist: pytest; extra == "test"
Provides-Extra: dev
Requires-Dist: pytest; extra == "dev"
Dynamic: license-file
